[{"queueId": 0, "map": "Custom games", "gameType": ""}, {"queueId": 70, "map": "Summoner's Rift", "gameType": "One for All"}, {"queueId": 72, "map": "Howling Abyss", "gameType": "1v1 Snowdown Showdown"}, {"queueId": 73, "map": "Howling Abyss", "gameType": "2v2 Snowdown Showdown"}, {"queueId": 75, "map": "Summoner's Rift", "gameType": "6v6 Hexakill"}, {"queueId": 76, "map": "Summoner's Rift", "gameType": "Ultra Rapid Fire"}, {"queueId": 78, "map": "Summoner's Rift", "gameType": "Mirrored One for"}, {"queueId": 83, "map": "Summoner's Rift", "gameType": "Co-op vs AI Ultra Rapid Fire"}, {"queueId": 98, "map": "Twisted Treeline", "gameType": "6v6 Hexakill"}, {"queueId": 100, "map": "Butcher's Bridge", "gameType": "5v5 ARAM"}, {"queueId": 310, "map": "Summoner's Rift", "gameType": "Nemesis"}, {"queueId": 313, "map": "Summoner's Rift", "gameType": "Black Market Brawlers"}, {"queueId": 317, "map": "Crystal Scar", "gameType": "Definitely Not Dominion"}, {"queueId": 325, "map": "Summoner's Rift", "gameType": "All Random"}, {"queueId": 400, "map": "Summoner's Rift", "gameType": "5v5 Draft Pick"}, {"queueId": 420, "map": "Summoner's Rift", "gameType": "5v5 Ranked Solo"}, {"queueId": 430, "map": "Summoner's Rift", "gameType": "5v5 Blind Pick"}, {"queueId": 440, "map": "Summoner's Rift", "gameType": "5v5 Ranked Flex"}, {"queueId": 450, "map": "Howling Abyss", "gameType": "5v5 ARAM"}, {"queueId": 460, "map": "Twisted Treeline", "gameType": "3v3 Blind Pick"}, {"queueId": 470, "map": "Twisted Treeline", "gameType": "3v3 Ranked Flex"}, {"queueId": 600, "map": "Summoner's Rift", "gameType": "Blood Hunt Assassin"}, {"queueId": 610, "map": "Cosmic Ruins", "gameType": "Dark Star: Singularity"}, {"queueId": 800, "map": "Twisted Treeline", "gameType": "Co-op vs. AI Intermediate Bot"}, {"queueId": 810, "map": "Twisted Treeline", "gameType": "Co-op vs. AI Intro Bot"}, {"queueId": 820, "map": "Twisted Treeline", "gameType": "Co-op vs. AI Beginner Bot"}, {"queueId": 830, "map": "Summoner's Rift", "gameType": "Co-op vs. AI Intro Bot"}, {"queueId": 840, "map": "Summoner's Rift", "gameType": "Co-op vs. AI Beginner Bot"}, {"queueId": 850, "map": "Summoner's Rift", "gameType": "Co-op vs. AI Intermediate Bot"}, {"queueId": 900, "map": "Summoner's Rift", "gameType": "ARURF"}, {"queueId": 910, "map": "Crystal Scar", "gameType": "Ascension"}, {"queueId": 920, "map": "Howling Abyss", "gameType": "Legend of the Poro King"}, {"queueId": 940, "map": "Summoner's Rift", "gameType": "Nexus Siege"}, {"queueId": 950, "map": "Summoner's Rift", "gameType": "Doom Bots Voting"}, {"queueId": 960, "map": "Summoner's Rift", "gameType": "Doom Bots Standard"}, {"queueId": 980, "map": "Valoran City Park", "gameType": "Star Guardian Invasion: Normal"}, {"queueId": 990, "map": "Valoran City Park", "gameType": "Star Guardian Invasion: Onslaught"}, {"queueId": 1000, "map": "Overcharge", "gameType": "PROJECT: Hunters"}, {"queueId": 1010, "map": "Summoner's Rift", "gameType": "Snow ARURF"}]